{
    "0": {
        "file": {
            "fileName": "monkey1.jpeg",
            "mimetype": "image/jpeg",
            "storageName": "21de458433a8b509bb649396f8896ac3",
            "size": 204170
        },
        "metadata": {
            "name": "monkey 1",
            "author": "RBG"
        },
        "ipfs": {
            "path": "QmTPrM7rm7Pn3xcHSKTHqk1P3hh73b7fneXLE52Zz13NrL",
            "cid": {
                "code": 112,
                "version": 0,
                "hash": {
                    "0": 18,
                    "1": 32,
                    "2": 75,
                    "3": 28,
                    "4": 86,
                    "5": 27,
                    "6": 35,
                    "7": 185,
                    "8": 66,
                    "9": 30,
                    "10": 121,
                    "11": 237,
                    "12": 54,
                    "13": 41,
                    "14": 143,
                    "15": 204,
                    "16": 63,
                    "17": 230,
                    "18": 130,
                    "19": 64,
                    "20": 69,
                    "21": 176,
                    "22": 135,
                    "23": 112,
                    "24": 237,
                    "25": 250,
                    "26": 114,
                    "27": 106,
                    "28": 107,
                    "29": 127,
                    "30": 20,
                    "31": 24,
                    "32": 248,
                    "33": 145
                }
            },
            "size": 204184
        }
    },
    "1": {
        "file": {
            "fileName": "monkey2.jpeg",
            "mimetype": "image/jpeg",
            "storageName": "556818f3591edf0fbe06df3cfca594c1",
            "size": 29823
        },
        "metadata": {
            "name": "monkey 2",
            "author": "RBG"
        },
        "ipfs": {
            "path": "QmRWjT4usWNXi7dEYU6mX9iUDqdjqM3jKC6mJGnqmVLago",
            "cid": {
                "code": 112,
                "version": 0,
                "hash": {
                    "0": 18,
                    "1": 32,
                    "2": 47,
                    "3": 40,
                    "4": 58,
                    "5": 173,
                    "6": 233,
                    "7": 223,
                    "8": 246,
                    "9": 58,
                    "10": 42,
                    "11": 243,
                    "12": 19,
                    "13": 94,
                    "14": 33,
                    "15": 85,
                    "16": 238,
                    "17": 152,
                    "18": 199,
                    "19": 171,
                    "20": 239,
                    "21": 134,
                    "22": 172,
                    "23": 150,
                    "24": 85,
                    "25": 113,
                    "26": 51,
                    "27": 203,
                    "28": 141,
                    "29": 87,
                    "30": 45,
                    "31": 209,
                    "32": 134,
                    "33": 96
                }
            },
            "size": 29837
        }
    },
    "2": {
        "file": {
            "fileName": "monkey3.jpeg",
            "mimetype": "image/jpeg",
            "storageName": "faaca67c86eed2b1a977e62a2b384046",
            "size": 62673
        },
        "metadata": {
            "name": "monkey 3",
            "author": "RBG"
        },
        "ipfs": {
            "path": "Qme5d7Wrdg21YVMyB18iEwmy9oHRRA3QGE5k4B2rLAKZj8",
            "cid": {
                "code": 112,
                "version": 0,
                "hash": {
                    "0": 18,
                    "1": 32,
                    "2": 233,
                    "3": 225,
                    "4": 121,
                    "5": 64,
                    "6": 0,
                    "7": 2,
                    "8": 85,
                    "9": 39,
                    "10": 3,
                    "11": 123,
                    "12": 248,
                    "13": 83,
                    "14": 168,
                    "15": 58,
                    "16": 144,
                    "17": 175,
                    "18": 112,
                    "19": 171,
                    "20": 197,
                    "21": 220,
                    "22": 210,
                    "23": 118,
                    "24": 233,
                    "25": 126,
                    "26": 205,
                    "27": 150,
                    "28": 207,
                    "29": 25,
                    "30": 40,
                    "31": 167,
                    "32": 38,
                    "33": 11
                }
            },
            "size": 62687
        }
    },
    "3": {
        "file": {
            "fileName": "monkey4.jpeg",
            "mimetype": "image/jpeg",
            "storageName": "1125702c653c04454927d6c948758ab8",
            "size": 217279
        },
        "metadata": {
            "name": "monkey 4",
            "author": "RBG"
        },
        "ipfs": {
            "path": "QmYjEsWPkpRUwvQGrGWMaiD8gDenuV7WBu3VE2DS6VMSng",
            "cid": {
                "code": 112,
                "version": 0,
                "hash": {
                    "0": 18,
                    "1": 32,
                    "2": 154,
                    "3": 94,
                    "4": 70,
                    "5": 53,
                    "6": 164,
                    "7": 186,
                    "8": 236,
                    "9": 100,
                    "10": 148,
                    "11": 103,
                    "12": 90,
                    "13": 31,
                    "14": 130,
                    "15": 85,
                    "16": 77,
                    "17": 36,
                    "18": 224,
                    "19": 239,
                    "20": 36,
                    "21": 113,
                    "22": 5,
                    "23": 182,
                    "24": 149,
                    "25": 204,
                    "26": 38,
                    "27": 181,
                    "28": 47,
                    "29": 196,
                    "30": 98,
                    "31": 38,
                    "32": 101,
                    "33": 29
                }
            },
            "size": 217293
        }
    },
    "4": {
        "file": {
            "fileName": "monkey5.jpeg",
            "mimetype": "image/jpeg",
            "storageName": "a90448216a8a5507cbb865530629f94d",
            "size": 281808
        },
        "metadata": {
            "name": "monkey 5",
            "author": "RBG"
        },
        "ipfs": {
            "path": "QmTQuTEPhykN748xxVttBS6vHmSPsmjSpNRTnykYAvRsCp",
            "cid": {
                "code": 112,
                "version": 0,
                "hash": {
                    "0": 18,
                    "1": 32,
                    "2": 75,
                    "3": 97,
                    "4": 109,
                    "5": 174,
                    "6": 10,
                    "7": 79,
                    "8": 68,
                    "9": 144,
                    "10": 51,
                    "11": 81,
                    "12": 231,
                    "13": 65,
                    "14": 40,
                    "15": 210,
                    "16": 29,
                    "17": 195,
                    "18": 72,
                    "19": 184,
                    "20": 118,
                    "21": 37,
                    "22": 168,
                    "23": 37,
                    "24": 74,
                    "25": 209,
                    "26": 149,
                    "27": 0,
                    "28": 108,
                    "29": 143,
                    "30": 21,
                    "31": 143,
                    "32": 5,
                    "33": 165
                }
            },
            "size": 281940
        }
    },
    "5": {
        "file": {
            "fileName": "monkey6.jpeg",
            "mimetype": "image/jpeg",
            "storageName": "76fb725b6e8b3411a4a688c36c2e87f2",
            "size": 40887
        },
        "metadata": {
            "name": "monkey 6",
            "author": "RBG"
        },
        "ipfs": {
            "path": "QmU2kKhxqVUZqaCm1tsm1ST1zXjmuLm1q4DbPPqqHDKZJp",
            "cid": {
                "code": 112,
                "version": 0,
                "hash": {
                    "0": 18,
                    "1": 32,
                    "2": 84,
                    "3": 144,
                    "4": 3,
                    "5": 184,
                    "6": 215,
                    "7": 216,
                    "8": 154,
                    "9": 119,
                    "10": 212,
                    "11": 167,
                    "12": 228,
                    "13": 255,
                    "14": 116,
                    "15": 0,
                    "16": 222,
                    "17": 88,
                    "18": 208,
                    "19": 224,
                    "20": 88,
                    "21": 9,
                    "22": 71,
                    "23": 147,
                    "24": 27,
                    "25": 42,
                    "26": 101,
                    "27": 114,
                    "28": 200,
                    "29": 198,
                    "30": 38,
                    "31": 132,
                    "32": 4,
                    "33": 25
                }
            },
            "size": 40901
        }
    },
    "6": {
        "file": {
            "fileName": "monkey7.jpeg",
            "mimetype": "image/jpeg",
            "storageName": "237876141d7a9b4720b3617993774f93",
            "size": 85750
        },
        "metadata": {
            "name": "monkey 7",
            "author": "RBG"
        },
        "ipfs": {
            "path": "QmT6zLAGbsgycZxztpBnWZtgXBM44hg3y9aCebjy4T6c3v",
            "cid": {
                "code": 112,
                "version": 0,
                "hash": {
                    "0": 18,
                    "1": 32,
                    "2": 70,
                    "3": 202,
                    "4": 125,
                    "5": 82,
                    "6": 154,
                    "7": 161,
                    "8": 175,
                    "9": 92,
                    "10": 225,
                    "11": 109,
                    "12": 94,
                    "13": 33,
                    "14": 62,
                    "15": 217,
                    "16": 87,
                    "17": 95,
                    "18": 217,
                    "19": 29,
                    "20": 89,
                    "21": 245,
                    "22": 40,
                    "23": 203,
                    "24": 80,
                    "25": 71,
                    "26": 172,
                    "27": 196,
                    "28": 127,
                    "29": 230,
                    "30": 134,
                    "31": 10,
                    "32": 242,
                    "33": 221
                }
            },
            "size": 85764
        }
    },
    "7": {
        "file": {
            "fileName": "monkey8.jpeg",
            "mimetype": "image/jpeg",
            "storageName": "0bb181c55dc6744c7633a900e6d0af08",
            "size": 50666
        },
        "metadata": {
            "name": "monkey 8",
            "author": "RBG"
        },
        "ipfs": {
            "path": "QmVwWWzBvRQPnW4aKCZ53uYTsaKGHvwYEGaDuvT3fstGb1",
            "cid": {
                "code": 112,
                "version": 0,
                "hash": {
                    "0": 18,
                    "1": 32,
                    "2": 112,
                    "3": 239,
                    "4": 223,
                    "5": 216,
                    "6": 66,
                    "7": 131,
                    "8": 210,
                    "9": 141,
                    "10": 161,
                    "11": 47,
                    "12": 98,
                    "13": 175,
                    "14": 198,
                    "15": 48,
                    "16": 52,
                    "17": 80,
                    "18": 250,
                    "19": 0,
                    "20": 71,
                    "21": 217,
                    "22": 214,
                    "23": 155,
                    "24": 119,
                    "25": 79,
                    "26": 114,
                    "27": 138,
                    "28": 114,
                    "29": 106,
                    "30": 7,
                    "31": 14,
                    "32": 200,
                    "33": 40
                }
            },
            "size": 50680
        }
    },
    "8": {
        "file": {
            "fileName": "monkey9.jpeg",
            "mimetype": "image/jpeg",
            "storageName": "590e31de7336320d0fcea2dbb1ff0bb6",
            "size": 37585
        },
        "metadata": {
            "name": "monkey 9",
            "author": "RBG"
        },
        "ipfs": {
            "path": "QmTC8FwmBekJiEMUdWS7eF67i53UDRv1vw2Tp2faVPWSFP",
            "cid": {
                "code": 112,
                "version": 0,
                "hash": {
                    "0": 18,
                    "1": 32,
                    "2": 72,
                    "3": 27,
                    "4": 91,
                    "5": 102,
                    "6": 122,
                    "7": 78,
                    "8": 108,
                    "9": 102,
                    "10": 169,
                    "11": 26,
                    "12": 76,
                    "13": 148,
                    "14": 129,
                    "15": 43,
                    "16": 186,
                    "17": 141,
                    "18": 23,
                    "19": 144,
                    "20": 202,
                    "21": 159,
                    "22": 132,
                    "23": 71,
                    "24": 133,
                    "25": 234,
                    "26": 78,
                    "27": 247,
                    "28": 171,
                    "29": 15,
                    "30": 160,
                    "31": 91,
                    "32": 115,
                    "33": 110
                }
            },
            "size": 37599
        }
    },
    "9": {
        "file": {
            "fileName": "monkey10.jpeg",
            "mimetype": "image/jpeg",
            "storageName": "c2625c62de5369d239e274c757fd9fdb",
            "size": 563394
        },
        "metadata": {
            "name": "monkey 10",
            "author": "RBG"
        },
        "ipfs": {
            "path": "QmWmindv6NqPqCr2qfTPuRWvidshh75esCxy4HmsfDtvBv",
            "cid": {
                "code": 112,
                "version": 0,
                "hash": {
                    "0": 18,
                    "1": 32,
                    "2": 125,
                    "3": 73,
                    "4": 160,
                    "5": 116,
                    "6": 110,
                    "7": 121,
                    "8": 29,
                    "9": 81,
                    "10": 223,
                    "11": 3,
                    "12": 249,
                    "13": 222,
                    "14": 166,
                    "15": 112,
                    "16": 1,
                    "17": 87,
                    "18": 237,
                    "19": 184,
                    "20": 200,
                    "21": 106,
                    "22": 213,
                    "23": 25,
                    "24": 182,
                    "25": 186,
                    "26": 38,
                    "27": 219,
                    "28": 103,
                    "29": 184,
                    "30": 129,
                    "31": 64,
                    "32": 143,
                    "33": 229
                }
            },
            "size": 563588
        }
    }
}